autochange/__init__.py
autochange/__main__.py
autochange/changelog.py
autochange/cli.py
autochange/conventional.py
autochange/launcher.py
autochange/version.py
autochange-0.1.1.dist-info/licenses/LICENSE
autochange-0.1.1.dist-info/METADATA
autochange-0.1.1.dist-info/WHEEL
autochange-0.1.1.dist-info/entry_points.txt
autochange-0.1.1.dist-info/top_level.txt
autochange-0.1.1.dist-info/RECORD
