Metadata-Version: 2.4
Name: autochange
Version: 0.1.1
Summary: Lightweight semantic version + changelog manager
Author: MJ Anglin
License-Expression: MIT
Project-URL: Changelog, https://github.com/clxrityy/autochange/blob/master/CHANGELOG.md
Project-URL: Homepage, https://github.com/clxrityy/autochange
Project-URL: Issues, https://github.com/clxrityy/autochange/issues
Project-URL: Repository, https://github.com/clxrityy/autochange.git
Keywords: changelog,semantic versioning,release,automation
Classifier: Programming Language :: Python :: 3
Classifier: Programming Language :: Python :: 3.8
Classifier: Programming Language :: Python :: 3.9
Classifier: Programming Language :: Python :: 3.10
Classifier: Programming Language :: Python :: 3.11
Classifier: Programming Language :: Python :: 3.12
Classifier: Programming Language :: Python :: 3.13
Classifier: Operating System :: OS Independent
Requires-Python: >=3.8
License-File: LICENSE
Requires-Dist: typer>=0.9.0
Requires-Dist: rich>=13.0.0
Provides-Extra: dev
Requires-Dist: pytest>=7.0.0; extra == "dev"
Requires-Dist: pytest-cov; extra == "dev"
Requires-Dist: hypothesis>=6.0.0; extra == "dev"
Provides-Extra: release
Requires-Dist: build; extra == "release"
Requires-Dist: twine; extra == "release"
Dynamic: license-file
